telegram_pydantic/__init__.py
telegram_pydantic/models/__init__.py
telegram_pydantic/models/callback_query.py
telegram_pydantic/models/location.py
telegram_pydantic/models/login_url.py
telegram_pydantic/models/message.py
telegram_pydantic/models/message_auto_delete_timer_changed.py
telegram_pydantic/models/message_entity.py
telegram_pydantic/models/message_id.py
telegram_pydantic/models/message_update.py
telegram_pydantic/models/photo_size.py
telegram_pydantic/models/proximity_alert_triggered.py
telegram_pydantic/models/user.py
telegram_pydantic/models/user_profile_photos.py
telegram_pydantic/models/venue.py
telegram_pydantic/models/chat/__init__.py
telegram_pydantic/models/chat/chat.py
telegram_pydantic/models/chat/chat_invite_link.py
telegram_pydantic/models/chat/chat_location.py
telegram_pydantic/models/chat/chat_member.py
telegram_pydantic/models/chat/chat_member_updated.py
telegram_pydantic/models/chat/chat_permissions.py
telegram_pydantic/models/chat/chat_photo.py
telegram_pydantic/models/games/__init__.py
telegram_pydantic/models/games/callback_game.py
telegram_pydantic/models/games/game.py
telegram_pydantic/models/inline_mode/__init__.py
telegram_pydantic/models/inline_mode/chosen_inline_result.py
telegram_pydantic/models/inline_mode/inline_query.py
telegram_pydantic/models/input_media/__init__.py
telegram_pydantic/models/input_media/input_media.py
telegram_pydantic/models/input_media/input_media_animation.py
telegram_pydantic/models/input_media/input_media_audio.py
telegram_pydantic/models/input_media/input_media_document.py
telegram_pydantic/models/input_media/input_media_video.py
telegram_pydantic/models/keyboard/__init__.py
telegram_pydantic/models/keyboard/inline_keyboard_button.py
telegram_pydantic/models/keyboard/inline_keyboard_markup.py
telegram_pydantic/models/media/__init__.py
telegram_pydantic/models/media/animation.py
telegram_pydantic/models/media/audio.py
telegram_pydantic/models/media/contact.py
telegram_pydantic/models/media/dice.py
pydantic_telegram-0.1.0.dist-info/METADATA
pydantic_telegram-0.1.0.dist-info/WHEEL
pydantic_telegram-0.1.0.dist-info/top_level.txt
pydantic_telegram-0.1.0.dist-info/RECORD
