Metadata-Version: 2.1
Name: pydantic-telegram
Version: 0.1.0
Summary: Pydantic classes creating telegram bots.
Home-page: UNKNOWN
Author: Daniel Miller
Author-email: danielmiller20@gmail.com
License: MIT
Platform: UNKNOWN
Classifier: Programming Language :: Python :: 3
Classifier: License :: OSI Approved :: MIT License
Classifier: Operating System :: OS Independent
Requires-Python: >=3.8
Requires-Dist: pydantic (>=1.8.2)
